LICENSE
README.md
setup.py
scdibs/__init__.py
scdibs.egg-info/PKG-INFO
scdibs.egg-info/SOURCES.txt
scdibs.egg-info/dependency_links.txt
scdibs.egg-info/requires.txt
scdibs.egg-info/top_level.txt