Metadata-Version: 2.1
Name: scdibs
Version: 0.0.1
Summary: Splicing dynamics based integration of scRNAseq batches.
Home-page: https://github.com/aron0093/DIBS
Download-URL: https://github.com/aron0093/DIBS/archive/v_001.tar.gz
Author: Revant Gupta
Author-email: revant.gupta.93@gmail.com
License: BSD 3-Clause License
Keywords: Batch integration,single-cell RNA sequencing,RNA velocity
Classifier: Development Status :: 3 - Alpha
Classifier: Intended Audience :: Science/Research
Classifier: Topic :: Software Development :: Build Tools
Classifier: License :: OSI Approved :: BSD License
Classifier: Programming Language :: Python :: 3.7
Classifier: Programming Language :: Python :: 3.8
License-File: LICENSE
